{
  "asOf": "2026-06-24T15:31:40.958657",
  "date": "2026-06-24",
  "stocks": {
    "600519.SH": {
      "market": "A",
      "code": "600519.SH",
      "name": "贵州茅台",
      "price": 1207.68,
      "yesterday_close": 1222.45,
      "open": 1222.65,
      "high": 1241.87,
      "low": 1207.51,
      "amount_yi": 55.1657446,
      "change_pct": -1.21,
      "amplitude": 2.81,
      "turnover": 0.363,
      "chg_5d": -3.82,
      "chg_20d": -5.16,
      "chg_ytd": -12.31,
      "pe_ttm": 18.252,
      "pb": 0.0,
      "dividend_yield": 4.3,
      "high_52w": 1568.0,
      "low_52w": 1205.0,
      "main_net_today_yi": -10.85312814,
      "main_net_5d_yi": -34.18425621,
      "main_net_5d_pct": -22.3692,
      "main_net_10d_yi": -43.10377104,
      "main_net_20d_yi": -79.49833417,
      "kline_5d": [
        1240.0,
        1215.0,
        1241.41,
        1222.45,
        1207.68
      ],
      "emoji": "🟢",
      "details": {
        "consensus": {
          "target_price": 1738.6361,
          "buy_count": 39,
          "overweight_count": 12,
          "total_ratings": 51
        },
        "capital_flow": {
          "market": "A",
          "main_buy_yi": 18.9262,
          "main_sell_yi": 29.7794
        },
        "connect": {
          "holding_pct": 4.69
        },
        "announcements": [
          {
            "title": "贵州茅台:2025年度股东会决议公告",
            "date": "2026-06-12",
            "snippet": "证券简称：贵州茅台 贵州茅台酒股份有限公司2025年度股东会决议公告 本公司及董事会全体成员保证公告内容不存在虚假记载、误导性陈述或者重大遗漏，并对其内容的真实"
          },
          {
            "title": "贵州茅台:第四届董事会2026年度第八次会议决议公告",
            "date": "2026-05-22",
            "snippet": "贵州茅台酒股份有限公司第四届董事会2026年度第八次会议决议公告 本公司董事会及全体董事保证本公告内容不存在任何虚假记载、误导性陈述或者重大遗漏，并对其内容的真"
          },
          {
            "title": "贵州茅台:关于聘任董事会秘书的公告",
            "date": "2026-05-22",
            "snippet": "贵州茅台酒股份有限公司关于聘任董事会秘书的公告 本公司董事会及全体董事保证本公告内容不存在任何虚假记载、误导性陈述或者重大遗漏，并对其内容的真实性、准确性和完整"
          }
        ],
        "news": [
          {
            "title": "贵州茅台聘任余思明为董秘、还兼任财务总监，曾任茅台集团机关纪委委员",
            "date": "2026-06-15",
            "snippet": "6月11日下午，贵州茅台在贵州省仁怀市茅台镇茅台会议中心召开2025年度股东会，来自全国千余名贵州茅台股东、机构投资者与分析师等齐聚一堂，其中私募大佬林园也现身"
          },
          {
            "title": "贵州茅台Wind ESG评级由A上调至AA",
            "date": "2026-06-16",
            "snippet": "香港万得通讯社报道，贵州茅台是中国白酒行业的龙头企业，主营高端白酒研发、生产与销售，品牌价值与市场占有率居行业首位。 近日，Wind ESG评级系统将贵州茅台评"
          },
          {
            "title": "贵州茅台拟分红逾350亿元",
            "date": "2026-06-21",
            "snippet": "2025年，贵州茅台营收1721亿元，同比下滑1.2%，净利润823.2亿元，同比下滑4.53%。 6月2日，贵州茅台曾发布2025年度股东会会议资料，在关于2"
          }
        ],
        "kline_20d": [
          1275.88,
          1279.0,
          1291.91,
          1271.1,
          1255.67,
          1240.0,
          1215.0,
          1241.41,
          1222.45,
          1207.68
        ]
      }
    },
    "601318.SH": {
      "market": "A",
      "code": "601318.SH",
      "name": "中国平安",
      "price": 49.12,
      "yesterday_close": 50.4,
      "open": 50.69,
      "high": 50.88,
      "low": 49.03,
      "amount_yi": 54.15518285,
      "change_pct": -2.54,
      "amplitude": 3.67,
      "turnover": 1.026,
      "chg_5d": -7.3,
      "chg_20d": -6.45,
      "chg_ytd": -25.78,
      "pe_ttm": 6.698,
      "pb": 0.0,
      "dividend_yield": 5.49,
      "high_52w": 72.4502,
      "low_52w": 48.66,
      "main_net_today_yi": -6.89616618,
      "main_net_5d_yi": -7.28596013,
      "main_net_5d_pct": -13.6131,
      "main_net_10d_yi": -11.59896148,
      "main_net_20d_yi": -24.80897644,
      "kline_5d": [
        52.76,
        49.38,
        51.98,
        50.4,
        49.12
      ],
      "emoji": "🟢",
      "details": {
        "consensus": {
          "target_price": 77.4679,
          "buy_count": 22,
          "overweight_count": 4,
          "total_ratings": 26
        },
        "capital_flow": {
          "market": "A",
          "main_buy_yi": 19.912,
          "main_sell_yi": 26.8081
        },
        "connect": {
          "holding_pct": 4.73
        },
        "announcements": [
          {
            "title": "中國平安<02318> - 公司章程修訂獲核准及不再設立監事會及執行董事辭任",
            "date": "2026-05-14",
            "snippet": "茲提述中國平安保險（集團）股份有限公司（「本公司」）日期為2025年12月16日的公告、2025年12月29日的通函以及2026年2月13日的投票結果公告。本公"
          },
          {
            "title": "中国平安:关于公司章程获国家金融监督管理总局核准及不再设立监事会的公告",
            "date": "2026-05-15",
            "snippet": "中国平安保险（集团）股份有限公司关于公司章程获国家金融监督管理总局核准及不再设立监事会的公告 中国平安保险（集团）股份有限公司（以下简称“本公司”）董事会及全体"
          },
          {
            "title": "中国平安:第十三届董事会第十四次会议决议公告",
            "date": "2026-04-29",
            "snippet": "中国平安保险（集团）股份有限公司第十三届董事会第十四次会议决议公告 中国平安保险（集团）股份有限公司（以下简称“本公司”）董事会及全体董事保证本公告内容不存在任"
          }
        ],
        "news": [
          {
            "title": "中国平安一季度净利润250亿降7.4%，营运利润增7.6%",
            "date": "2026-04-28",
            "snippet": "3月28日，中国平安保险（集团）股份有限公司（中国平安，601318.SH；02318.HK）于港交所披露的2026年一季报显示，今年第一季度，该公司实现归属于"
          },
          {
            "title": "中国平安再获全球权威认证！",
            "date": "2026-05-14",
            "snippet": "一季度业绩稳健落地 摩根士丹利的评价并非空中楼阁。中国平安2026年一季度的业绩数据，恰好印证了这份报告中提及的核心竞争力。 数据显示，2026 年一季度，中国"
          },
          {
            "title": "中国平安(601318.SH)一季度归母净利润250.22亿元 新能源车险原保险保费收入同比提升16.1%",
            "date": "2026-04-29",
            "snippet": "智通财经APP讯，中国平安(601318.SH)发布2026年第一季度报告，第一季度，公司实现营业收入2184.05亿元，同比下降6.20%。归属于上市公司股东"
          }
        ],
        "kline_20d": [
          53.22,
          52.64,
          54.01,
          54.23,
          52.99,
          52.76,
          49.38,
          51.98,
          50.4,
          49.12
        ]
      }
    },
    "000858.SZ": {
      "market": "A",
      "code": "000858.SZ",
      "name": "五粮液",
      "price": 73.3,
      "yesterday_close": 74.76,
      "open": 74.54,
      "high": 75.45,
      "low": 73.28,
      "amount_yi": 22.1870413,
      "change_pct": -1.95,
      "amplitude": 2.9,
      "turnover": 0.773,
      "chg_5d": -6.42,
      "chg_20d": -12.07,
      "chg_ytd": -30.81,
      "pe_ttm": 22.58,
      "pb": 0.0,
      "dividend_yield": 7.03,
      "high_52w": 128.85,
      "low_52w": 74.37,
      "main_net_today_yi": -1.09882032,
      "main_net_5d_yi": -1.75091759,
      "main_net_5d_pct": -6.3028,
      "main_net_10d_yi": 0.04854138,
      "main_net_20d_yi": -4.02508618,
      "kline_5d": [
        77.49,
        75.85,
        76.55,
        74.76,
        73.3
      ],
      "emoji": "🟢",
      "details": {
        "consensus": {
          "target_price": 87.965,
          "buy_count": 13,
          "overweight_count": 1,
          "total_ratings": 16
        },
        "capital_flow": {
          "market": "A",
          "main_buy_yi": 6.3293,
          "main_sell_yi": 7.4281
        },
        "connect": {
          "holding_pct": 2.1
        },
        "announcements": [
          {
            "title": "五 粮 液:第七届董事会2026年第6次会议决议公告",
            "date": "2026-06-09",
            "snippet": "宜宾五粮液股份有限公司第七届董事会2026年第6次会议决议公告 本公司及董事会全体成员保证信息披露内容的真实、准确和完整，没有虚假记载、误导性陈述或重大遗漏。"
          },
          {
            "title": "五 粮 液:第七届董事会2026年第5次会议决议公告",
            "date": "2026-06-02",
            "snippet": "宜宾五粮液股份有限公司第七届董事会2026年第5次会议决议公告 本公司及董事会全体成员保证信息披露内容的真实、准确和完整，没有虚假记载、误导性陈述或重大遗漏。"
          },
          {
            "title": "五 粮 液:关于回购股份事项通知债权人的公告",
            "date": "2026-05-19",
            "snippet": "宜宾五粮液股份有限公司（以下简称公司）于2026年5月18日召开2026年第一次临时股东会，审议通过了《关于以集中竞价交易方式回购公司股份的议案》（以下简称回购"
          }
        ],
        "news": [
          {
            "title": "五粮液迎新帅：邓敏已任五粮液集团党委书记，拟任集团董事长",
            "date": "2026-06-08",
            "snippet": "白酒龙头五粮液迎来关键人事更迭。6月8日晚间，五粮液发布公告显示，邓敏已任四川省宜宾五粮液集团有限公司党委书记、董事，宜宾五粮液股份有限公司党委书记。拟任四川省"
          },
          {
            "title": "五粮液“蒸馏”五粮液",
            "date": "2026-05-11",
            "snippet": "一号说： 20年来头一遭的信任危机 2026年4月30日，五粮液（000858.SZ）终于发布了“难产”的2025年年报。 这份年报，直接刷新了资本市场对A股“"
          },
          {
            "title": "邓敏正式接任五粮液集团董事长",
            "date": "2026-06-15",
            "snippet": "未来展望：国资赋能 + 改革深化，龙头重塑可期 作为浓香型白酒龙头，五粮液拥有 3.2 万口明清古窖池群、20 万吨 / 年优质基酒产能等不可复制的核心资产，千"
          }
        ],
        "kline_20d": [
          79.14,
          79.79,
          79.92,
          79.63,
          78.33,
          77.49,
          75.85,
          76.55,
          74.76,
          73.3
        ]
      }
    },
    "300750.SZ": {
      "market": "A",
      "code": "300750.SZ",
      "name": "宁德时代",
      "price": 395.36,
      "yesterday_close": 392.51,
      "open": 392.0,
      "high": 399.27,
      "low": 386.66,
      "amount_yi": 135.21407676,
      "change_pct": 0.73,
      "amplitude": 3.21,
      "turnover": 0.809,
      "chg_5d": -2.02,
      "chg_20d": -1.77,
      "chg_ytd": 9.34,
      "pe_ttm": 23.161,
      "pb": 0.0,
      "dividend_yield": 2.0,
      "high_52w": 468.75,
      "low_52w": 241.33,
      "main_net_today_yi": 0.90725437,
      "main_net_5d_yi": -4.1078432,
      "main_net_5d_pct": -2.884,
      "main_net_10d_yi": -14.69482213,
      "main_net_20d_yi": -85.3326964,
      "kline_5d": [
        399.0,
        391.55,
        408.98,
        392.51,
        395.36
      ],
      "emoji": "🔴",
      "details": {
        "consensus": {
          "target_price": 542.5359,
          "buy_count": 24,
          "overweight_count": 13,
          "total_ratings": 37
        },
        "capital_flow": {
          "market": "A",
          "main_buy_yi": 65.5708,
          "main_sell_yi": 64.6636
        },
        "connect": {
          "holding_pct": 17.27
        },
        "announcements": [],
        "news": [
          {
            "title": "宁德时代股价涨3.17%",
            "date": "2026-05-29",
            "snippet": "来源：新浪基金∞工作室 5月29日，宁德时代涨3.17%，截至发稿，报428.87元/股，成交94.97亿元，换手率0.53%，总市值19841.71亿元。 资"
          },
          {
            "title": "胜遇信用观澜 ‖ 宁德时代：何以为王",
            "date": "2026-06-19",
            "snippet": "2026年6月16日，宁德时代新能源科技股份有限公司（以下简称“宁德时代”或“公司”）发行20亿元‌科技创新公司债券‌（2026年第二期），这也是宁德时代202"
          },
          {
            "title": "宁德时代投入济宁基地超87亿",
            "date": "2026-05-29",
            "snippet": "◆导报记者 孙罗南 济南报道 动力电池龙头企业宁德时代新能源科技股份有限公司(下称“宁德时代”)再次启动融资。5月27日,宁德时代披露《2026年度第三期绿色科"
          }
        ],
        "kline_20d": [
          388.5,
          382.2,
          394.85,
          398.1,
          403.53,
          399.0,
          391.55,
          408.98,
          392.51,
          395.36
        ]
      }
    },
    "688981.SH": {
      "market": "A",
      "code": "688981.SH",
      "name": "中芯国际",
      "price": 151.53,
      "yesterday_close": 141.7,
      "open": 141.5,
      "high": 156.35,
      "low": 141.32,
      "amount_yi": 211.60854009,
      "change_pct": 6.94,
      "amplitude": 10.61,
      "turnover": 7.06,
      "chg_5d": 16.44,
      "chg_20d": 1.58,
      "chg_ytd": 23.37,
      "pe_ttm": 240.664,
      "pb": 0.0,
      "dividend_yield": 0.0,
      "high_52w": 159.05,
      "low_52w": 84.86,
      "main_net_today_yi": 24.22319389,
      "main_net_5d_yi": 11.69637522,
      "main_net_5d_pct": 36.287000000000006,
      "main_net_10d_yi": -12.0022136,
      "main_net_20d_yi": -84.26048409,
      "kline_5d": [
        134.7,
        140.7,
        145.59,
        141.7,
        151.53
      ],
      "emoji": "🔴",
      "details": {
        "consensus": {
          "target_price": 163.8733,
          "buy_count": 7,
          "overweight_count": 3,
          "total_ratings": 10
        },
        "capital_flow": {
          "market": "A",
          "main_buy_yi": 116.7183,
          "main_sell_yi": 92.4951
        },
        "connect": {
          "holding_pct": 0.39
        },
        "announcements": [
          {
            "title": "中芯國際<00981> - 2025年度利潤分配方案; 建議開展套期保值業務; 續聘審計師及釐定2026年度審計費用; 重選董事及授權董事會釐定董事酬金; 建議授出發行及購回股份之一般授權; 建議修訂組織章程細則及相關內部制度; 年度股東會通告",
            "date": "2026-06-03",
            "snippet": "閣下如對本通函之任何內容或對應採取的行動有疑問，應諮詢閣下之股票經紀或其他註冊證券交易商、銀行經理、律師、專業會計師或其他專業顧問。 閣下如已將名下之中芯國際集"
          }
        ],
        "news": [
          {
            "title": "中芯国际(688981)：中芯国际完成对中芯北方收购 强化内部协同并优化供应链",
            "date": "2026-06-23",
            "snippet": "事件 中芯国际公告，公司已完成向中芯北方集成电路制造（北京）有限公司支付购买资产款项，本次交易涉及标的资产的过户手续已经办理完毕。 中芯国际完成对中芯北方收购后"
          },
          {
            "title": "中芯国际一季度利润约为13.61亿元，同比增加0.4%",
            "date": "2026-05-15",
            "snippet": "5月14日晚，中芯国际（688981.SH）发布一季度业绩公告称，2026年第一季度营收约176.17亿元，同比增加8.1%；归属于上市公司股东的净利润约13."
          },
          {
            "title": "中芯国际用DUV光刻机+创新方案，做出了媲美台积电3nm先进制程性能的芯片，把差距缩短到了两年以内",
            "date": "2026-05-21",
            "snippet": "（来源：宏策股） 关于中芯国际的一个产业逻辑，中信建投 人工智能首席于方博： 核心一句话：中芯国际用DUV光刻机+创新方案，做出了媲美台积电3nm先进制程性能的"
          }
        ],
        "kline_20d": [
          125.34,
          127.4,
          124.88,
          130.52,
          130.14,
          134.7,
          140.7,
          145.59,
          141.7,
          151.53
        ]
      }
    },
    "01810.HK": {
      "market": "HK",
      "code": "01810.HK",
      "name": "小米集团-W",
      "price": 22.88,
      "yesterday_close": 22.62,
      "open": 22.62,
      "high": 23.16,
      "low": 22.26,
      "amount_yi": 42.56943468,
      "change_pct": 1.15,
      "amplitude": 3.98,
      "chg_5d": -10.83,
      "chg_20d": -23.12,
      "chg_ytd": -41.78,
      "pe_ttm": 14.73,
      "pb": 0.0,
      "high_52w": 61.45,
      "low_52w": 22.5,
      "kline_5d": [
        25.42,
        24.58,
        23.72,
        22.62,
        22.88
      ],
      "currency": "HKD",
      "emoji": "🔴",
      "details": {
        "consensus": {
          "target_price": 42.4894,
          "buy_count": 16,
          "overweight_count": 18,
          "total_ratings": 42
        },
        "capital_flow": {
          "market": "HK",
          "short_trend_5d": []
        },
        "connect": {
          "holding_pct": 20.29
        },
        "announcements": [
          {
            "title": "小米集團－Ｗ<01810> - 建議授出購回股份及發行股份之一般授權、建議重選退任董事、建議採納新組織章程大綱及細則及股東週年大會通告",
            "date": "2026-04-28",
            "snippet": "小米集團謹訂於2026年6月2日（星期二）下午二時正假座中華人民共和國北京海淀區安寧莊路小米科技園舉行股東週年大會，大會通告載於本通函第24至27頁。亦隨附股東"
          },
          {
            "title": "小米集團－Ｗ<01810> - 自動股份購回計劃公告",
            "date": "2026-01-22",
            "snippet": "小米集團（「本公司」）董事會（「董事會」）欣然宣佈，本公司於2026年1月22日與一家獨立經紀商（「經紀商」）訂立協議（「經紀協議」），據此，經紀商將根據經紀協"
          },
          {
            "title": "小米集團－Ｗ<01810> - 持續關連交易終止現有合約安排及訂立新合約安排",
            "date": "2026-04-02",
            "snippet": "(iv) 北京小米電子軟件、洪鋒及劉凌迪訂立股權轉讓協議，據此，洪鋒同意向劉凌迪轉讓北京小米電子軟件的10%股權（「股權轉讓協議」）（(i)至(iv)統稱為「股"
          }
        ],
        "news": [
          {
            "title": "小米集团-W：于6月18日回购800万股，回购金额1.97亿港元",
            "date": "2026-06-18",
            "snippet": "香港万得通讯社报道，小米集团-W在港交所公告，公司于2026年6月18日，通过集中竞价交易回购800万股，回购金额1.97亿港元，最低成交价为24.38港元，最"
          },
          {
            "title": "小米集团-W：于6月17日回购400万股，回购金额1.01亿港元",
            "date": "2026-06-17",
            "snippet": "香港万得通讯社报道，小米集团-W在港交所公告，公司于2026年6月17日，通过集中竞价交易回购400万股，回购金额1.01亿港元，最低成交价为25.28港元，最"
          },
          {
            "title": "小米集团-W：于6月5日回购350万股，回购金额9803.08万港元",
            "date": "2026-06-05",
            "snippet": "香港万得通讯社报道，小米集团-W在港交所公告，公司于2026年6月5日，通过集中竞价交易回购350万股，回购金额9803.08万港元，最低成交价为27.98港元"
          }
        ],
        "kline_20d": [
          26.32,
          25.84,
          26.2,
          26.26,
          25.66,
          25.42,
          24.58,
          23.72,
          22.62,
          22.88
        ]
      }
    },
    "00700.HK": {
      "market": "HK",
      "code": "00700.HK",
      "name": "腾讯控股",
      "price": 429.4,
      "yesterday_close": 414.8,
      "open": 414.0,
      "high": 439.8,
      "low": 412.6,
      "amount_yi": 142.44186085,
      "change_pct": 3.52,
      "amplitude": 6.56,
      "chg_5d": -4.02,
      "chg_20d": -2.19,
      "chg_ytd": -27.48,
      "pe_ttm": 14.688,
      "pb": 0.0,
      "high_52w": 675.134,
      "low_52w": 413.6,
      "kline_5d": [
        445.4,
        440.2,
        433.0,
        414.8,
        429.6
      ],
      "currency": "HKD",
      "emoji": "🔴",
      "details": {
        "consensus": {
          "target_price": 706.5872,
          "buy_count": 24,
          "overweight_count": 28,
          "total_ratings": 53
        },
        "capital_flow": {
          "market": "HK",
          "short_trend_5d": []
        },
        "connect": {
          "holding_pct": 11.62
        },
        "announcements": [
          {
            "title": "騰訊控股<00700> - 董事會會議召開日期",
            "date": "2026-03-23",
            "snippet": "香港交易及結算所有限公司及香港聯合交易所有限公司對本公告的內容概不負責，對其準確性或完整性亦不發表任何聲明，並明確表示，概不對因本公告全部或任何部份內容而產生或"
          },
          {
            "title": "騰訊控股<00700> - 截至二零二五年十二月三十一日止年度末期股息",
            "date": "2026-03-18",
            "snippet": "免責聲明 香港交易及結算所有限公司及香港聯合交易所有限公司對本公告的內容概不負責，對其準確性或完整性亦不發表任何聲明，並明確表示，概不對因公告全部或任何部份內容"
          },
          {
            "title": "Form SCHEDULE 13D/A 腾讯控股-ADR :  General Statement of Acquisition of Beneficial Ownership",
            "date": "2025-07-08",
            "snippet": "该表格为腾讯控股有限公司与腾讯移动有限公司的签署文件，包含签名、姓名/职务及日期三个字段，签署人为Wang Sze Man，职务为授权签字人，签署日期为07/0"
          }
        ],
        "news": [
          {
            "title": "腾讯控股涨超4%",
            "date": "2026-06-09",
            "snippet": "2026-06-09 09:57:01 【腾讯控股涨超4%】腾讯控股涨超4%，消息面上，据2026年6月8日消息，微信正式面向开发者提供接入微信AI生态的能力，"
          },
          {
            "title": "腾讯控股：6月12日购回108.1万股，耗资约5.01亿港元",
            "date": "2026-06-12",
            "snippet": "2026-06-12 17:51:42 【腾讯控股：6月12日购回108.1万股，耗资约5.01亿港元】腾讯控股公告，公司于2026年6月12日在香港联交所购回"
          },
          {
            "title": "天风证券：推荐腾讯控股为2026年6月金股",
            "date": "2026-06-01",
            "snippet": "香港万得通讯社报道，天风证券6月1日发布报告，将腾讯控股推荐为2026年6月金股。截至目前，共有1家券商推荐腾讯控股为2026年6月金股，较上月减少3个，近3个"
          }
        ],
        "kline_20d": [
          465.6,
          457.2,
          463.6,
          459.6,
          447.4,
          445.4,
          440.2,
          433.0,
          414.8,
          429.4
        ]
      }
    },
    "03690.HK": {
      "market": "HK",
      "code": "03690.HK",
      "name": "美团-W",
      "price": 67.95,
      "yesterday_close": 69.6,
      "open": 69.3,
      "high": 70.0,
      "low": 67.55,
      "amount_yi": 25.79196011,
      "change_pct": -2.37,
      "amplitude": 3.52,
      "chg_5d": -9.76,
      "chg_20d": -13.77,
      "chg_ytd": -34.22,
      "pe_ttm": -9.206,
      "pb": 0.0,
      "high_52w": 136.1,
      "low_52w": 69.2,
      "kline_5d": [
        74.4,
        71.8,
        72.0,
        69.6,
        67.95
      ],
      "currency": "HKD",
      "emoji": "🟢",
      "details": {
        "consensus": {
          "target_price": 114.5338,
          "buy_count": 18,
          "overweight_count": 18,
          "total_ratings": 40
        },
        "capital_flow": {
          "market": "HK",
          "short_amount_today_yi": 4.5792
        },
        "connect": {
          "holding_pct": 20.89
        },
        "announcements": [
          {
            "title": "美團－Ｗ<03690> - (1)獨立非執行董事退任及建議選舉獨立非執行董事；及(2)董事委員會組成變動",
            "date": "2026-06-04",
            "snippet": "美团（「本公司」，連同其附屬公司及綜合聯屬實體，統稱「本集團」）的董事會（「董事會」）欣然宣佈，於2026年6月4日，姚建華先生（「姚先生」）已由董事會提名，並"
          },
          {
            "title": "美團－Ｗ<03690> - 董事會會議召開日期",
            "date": "2026-05-19",
            "snippet": "香港交易及結算所有限公司及香港聯合交易所有限公司對本公告的內容概不負責，對其準確性或完整性亦不發表任何聲明，並明確表示，概不對因本公告全部或任何部份內容而產生或"
          },
          {
            "title": "美團－Ｗ<03690> - 董事會會議召開日期",
            "date": "2026-03-16",
            "snippet": "香港交易及結算所有限公司及香港聯合交易所有限公司對本公告的內容概不負責，對其準確性或完整性亦不發表任何聲明，並明確表示，概不對因本公告全部或任何部分內容而產生或"
          }
        ],
        "news": [
          {
            "title": "美团-W(03690)绩前上涨3.68% 市场料26Q1实现营收911.08亿元&Keeta海外贡献长期价值",
            "date": "2026-06-01",
            "snippet": "金吾财讯 | 美团-W(03690)盘初走高，涨3.68%，最新报76.15港元，成交额8.64亿港元。 消息面上，该公司将于今日(6月1日)发布一季度财报，引"
          },
          {
            "title": "中银国际发布研报称，美团-W(03690.HK)第一季总收入同比增长6%至910亿元人民币(下同)，符合市场预期",
            "date": "2026-06-03",
            "snippet": "中银国际发布研报称，美团-W(03690.HK)第一季总收入同比增长6%至910亿元人民币(下同)，符合市场预期。受惠于外卖业务单位经济(UE)改善优于预期，预"
          },
          {
            "title": "【券商聚焦】开源证券维持美团-W(03690)“买入”评级 指核心商业亏损环比显著改善",
            "date": "2026-06-05",
            "snippet": "金吾财讯|开源证券发布研报指，维持美团-W(03690.HK)“买入”评级。研报认为，短期外卖竞争回归理性，核心商业亏损环比显著改善，海外新业务快速增长；中长期"
          }
        ],
        "kline_20d": [
          79.0,
          78.1,
          77.9,
          78.25,
          75.3,
          74.4,
          71.8,
          72.0,
          69.6,
          67.85
        ]
      }
    },
    "01211.HK": {
      "market": "HK",
      "code": "01211.HK",
      "name": "比亚迪股份",
      "price": 75.9,
      "yesterday_close": 75.85,
      "open": 76.2,
      "high": 76.85,
      "low": 74.2,
      "amount_yi": 17.6778875,
      "change_pct": 0.07,
      "amplitude": 3.49,
      "chg_5d": -9.7,
      "chg_20d": -18.57,
      "chg_ytd": -20.02,
      "pe_ttm": 22.417,
      "pb": 0.0,
      "high_52w": 135.653,
      "low_52w": 75.6,
      "kline_5d": [
        81.9,
        80.85,
        78.35,
        75.85,
        75.9
      ],
      "currency": "HKD",
      "emoji": "🔴",
      "details": {
        "consensus": {
          "target_price": 126.2723,
          "buy_count": 6,
          "overweight_count": 17,
          "total_ratings": 25
        },
        "capital_flow": {
          "market": "HK",
          "short_trend_5d": []
        },
        "connect": {
          "holding_pct": 10.24
        },
        "announcements": [
          {
            "title": "比亞迪股份<01211> - 截至二零二五年十二月三十一日止年度之末期股息（更新）",
            "date": "2026-06-09",
            "snippet": "## 股票發行人現金股息（可選擇貨幣）公告 <table id='953c4ed04df20f7ea8e696ba9642a367' titleId='ca7f"
          }
        ],
        "news": [
          {
            "title": "比亚迪AH股齐涨，比亚迪A股涨超3%，比亚迪股份(01211.HK)H股涨超2%",
            "date": "2026-05-29",
            "snippet": "2026-05-29 09:26:59 比亚迪AH股齐涨，比亚迪A股涨超3%，比亚迪股份(01211.HK)H股涨超2%；公司日前发布自研4nm制程智驾芯片璇玑"
          },
          {
            "title": "中信证券：维持比亚迪股份买入评级",
            "date": "2026-06-03",
            "snippet": "【中信证券：维持比亚迪股份买入评级】财联社6月3日电，中信证券发布关于比亚迪股份（01211.HK）的研报，维持“买入”评级。公司推出天神之眼5.0智能驾驶系统"
          },
          {
            "title": "交银国际：给予比亚迪股份买入评级",
            "date": "2026-06-01",
            "snippet": "【交银国际：给予比亚迪股份买入评级】财联社6月1日电，交银国际发布关于比亚迪股份（01211.HK）的研报，给予“买入”评级。公司通过天神之眼智驾体系、自研高算"
          }
        ],
        "kline_20d": [
          86.189,
          84.95,
          86.55,
          85.6,
          84.05,
          81.9,
          80.85,
          78.35,
          75.85,
          75.9
        ]
      }
    },
    "09988.HK": {
      "market": "HK",
      "code": "09988.HK",
      "name": "阿里巴巴-W",
      "price": 99.65,
      "yesterday_close": 98.95,
      "open": 99.15,
      "high": 101.5,
      "low": 97.65,
      "amount_yi": 87.89069078,
      "change_pct": 0.71,
      "amplitude": 3.89,
      "chg_5d": -6.87,
      "chg_20d": -21.21,
      "chg_ytd": -29.6,
      "pe_ttm": 15.957,
      "pb": 0.0,
      "high_52w": 184.564,
      "low_52w": 98.7,
      "kline_5d": [
        106.9,
        104.9,
        102.9,
        98.95,
        99.65
      ],
      "currency": "HKD",
      "emoji": "🔴",
      "details": {
        "consensus": {
          "target_price": 190.3169,
          "buy_count": 28,
          "overweight_count": 16,
          "total_ratings": 44
        },
        "capital_flow": {
          "market": "HK",
          "short_trend_5d": []
        },
        "connect": {
          "holding_pct": 10.29
        },
        "announcements": [
          {
            "title": "阿里巴巴－Ｗ<09988> - 2026財務年度報告",
            "date": "2026-06-18",
            "snippet": "阿里巴巴集團控股有限公司 紐交所代碼：BABA 港交所代號：9988 （港幣櫃台） 89988 （人民幣櫃台） [- AI驅動 邁向未來 2026 財務年度報告"
          },
          {
            "title": "阿里巴巴－Ｗ<09988> - 截至2026年3月31日止年度的股息",
            "date": "2026-05-13",
            "snippet": "免責聲明 香港交易及結算所有限公司及香港聯合交易所有限公司對本公告的內容概不負責，對其準確性或完整性亦不發表任何聲明，並明確表示，概不對因公告全部或任何部份內容"
          },
          {
            "title": "阿里巴巴－Ｗ<09988> - 自願公告 股息派發流程細節",
            "date": "2026-05-28",
            "snippet": "香港交易及結算所有限公司及香港聯合交易所有限公司（「香港聯交所」）對本公告的內容概不負責，對其準確性或完整性亦不發表任何聲明，並明確表示概不會就本公告全部或任何"
          }
        ],
        "news": [
          {
            "title": "阿里巴巴-W：调整2031年到期可转换优先票据转换率，已提交额外股份上市申请",
            "date": "2026-06-18",
            "snippet": "香港万得通讯社报道，阿里巴巴-W2026年6月18日公告称，香港交易及结算所有限公司及香港联合交易所有限公司对本公告内容概不负责，不对其准确性或完整性发表任何声"
          },
          {
            "title": "阿里巴巴-W：调整2032年到期可转换优先票据转换率，已提交额外股份上市申请",
            "date": "2026-06-18",
            "snippet": "香港万得通讯社报道，阿里巴巴-W2026年6月18日公告称，香港交易及结算所有限公司及香港联合交易所有限公司对本公告内容概不负责，对其准确性或完整性亦不发表任何"
          },
          {
            "title": "阿里巴巴-W(09988)发布年度业绩，收入10236.70亿元 同比增长3%",
            "date": "2026-05-13",
            "snippet": "智通财经APP讯，阿里巴巴-W(09988)发布2026年三月底止季度业绩，该集团取得收入人民币2433.8亿元，同比增长3%。若不考虑高鑫零售和银泰的已处置业"
          }
        ],
        "kline_20d": [
          113.5,
          107.4,
          110.2,
          109.3,
          107.0,
          106.9,
          104.9,
          102.9,
          98.95,
          99.6
        ]
      }
    }
  }
}
